features/__init__.py
features/_compat.py
features/bases.py
features/config.ini
features/meta.py
features/parsers.py
features/systems.py
features/tools.py
features/visualize.py
features-0.5.12.dist-info/LICENSE.txt
features-0.5.12.dist-info/METADATA
features-0.5.12.dist-info/WHEEL
features-0.5.12.dist-info/top_level.txt
features-0.5.12.dist-info/RECORD
